WowFile/__init__.py
WowFile/__main__.py
WowFile/_version.py
WowFile/tkViewer.py
WowFile/wow.py
wowfile-0.3.2.post3.data/scripts/wowviewer
wowfile-0.3.2.post3.dist-info/COPYING
wowfile-0.3.2.post3.dist-info/METADATA
wowfile-0.3.2.post3.dist-info/WHEEL
wowfile-0.3.2.post3.dist-info/top_level.txt
wowfile-0.3.2.post3.dist-info/RECORD
