Metadata-Version: 2.1
Name: wowfile
Version: 0.3.2.post3
Summary: A library and simple viewer to manipulate SparkMaker WOW files
Home-page: https://github.com/Godzil/WoWTools
Author: Manoel <godzil> Trapier
Author-email: wowfile@godzil.net
License: UNKNOWN
Platform: UNKNOWN
Classifier: Programming Language :: Python :: 3
Classifier: Operating System :: OS Independent
Classifier: Development Status :: 4 - Beta
Classifier: License :: OSI Approved :: GNU General Public License v2 (GPLv2)
Requires-Python: >=3.6
Requires-Dist: Pillow
